setup.cfg
setup.py
agm_env_helper/__init__.py
agm_env_helper/env_helper.py
agm_env_helper.egg-info/PKG-INFO
agm_env_helper.egg-info/SOURCES.txt
agm_env_helper.egg-info/dependency_links.txt
agm_env_helper.egg-info/not-zip-safe
agm_env_helper.egg-info/top_level.txt