Metadata-Version: 2.1
Name: agm-env-helper
Version: 0.1.1
Summary: Custom env helper
Home-page: UNKNOWN
Author-email: alexgeniusman@gmail.com
License: UNKNOWN
Platform: UNKNOWN
